withref.py
withref-0.3.3.dist-info/DESCRIPTION.rst
withref-0.3.3.dist-info/METADATA
withref-0.3.3.dist-info/RECORD
withref-0.3.3.dist-info/WHEEL
withref-0.3.3.dist-info/metadata.json
withref-0.3.3.dist-info/top_level.txt
